[
  {
    "anonymous": false,
    "inputs": [
      {
        "indexed": false,
        "internalType": "uint256",
        "name": "maxHoldingBaseAsset",
        "type": "uint256"
      },
      {
        "indexed": false,
        "internalType": "uint256",
        "name": "openInterestNotionalCap",
        "type": "uint256"
      }
    ],
    "name": "CapChanged",
    "type": "event"
  },
  {
    "anonymous": false,
    "inputs": [
      {
        "indexed": false,
        "internalType": "int256",
        "name": "rate",
        "type": "int256"
      },
      {
        "indexed": false,
        "internalType": "uint256",
        "name": "underlyingPrice",
        "type": "uint256"
      }
    ],
    "name": "FundingRateUpdated",
    "type": "event"
  },
  {
    "anonymous": false,
    "inputs": [
      {
        "indexed": false,
        "internalType": "uint256",
        "name": "quoteReserve",
        "type": "uint256"
      },
      {
        "indexed": false,
        "internalType": "uint256",
        "name": "baseReserve",
        "type": "uint256"
      },
      {
        "indexed": false,
        "internalType": "int256",
        "name": "cumulativeNotional",
        "type": "int256"
      }
    ],
    "name": "LiquidityChanged",
    "type": "event"
  },
  {
    "anonymous": false,
    "inputs": [
      {
        "indexed": false,
        "internalType": "uint256",
        "name": "ammPrice",
        "type": "uint256"
      },
      {
        "indexed": false,
        "internalType": "uint256",
        "name": "oraclePrice",
        "type": "uint256"
      },
      {
        "indexed": false,
        "internalType": "uint256",
        "name": "adjustPrice",
        "type": "uint256"
      },
      {
        "indexed": false,
        "internalType": "int256",
        "name": "MMLiquidity",
        "type": "int256"
      },
      {
        "indexed": false,
        "internalType": "int256",
        "name": "MMPNL",
        "type": "int256"
      },
      {
        "indexed": false,
        "internalType": "bool",
        "name": "moved",
        "type": "bool"
      }
    ],
    "name": "MoveAMMPrice",
    "type": "event"
  },
  {
    "anonymous": false,
    "inputs": [
      {
        "indexed": true,
        "internalType": "address",
        "name": "previousOwner",
        "type": "address"
      },
      {
        "indexed": true,
        "internalType": "address",
        "name": "newOwner",
        "type": "address"
      }
    ],
    "name": "OwnershipTransferred",
    "type": "event"
  },
  {
    "anonymous": false,
    "inputs": [
      {
        "indexed": false,
        "internalType": "uint256",
        "name": "quoteAssetReserve",
        "type": "uint256"
      },
      {
        "indexed": false,
        "internalType": "uint256",
        "name": "baseAssetReserve",
        "type": "uint256"
      },
      {
        "indexed": false,
        "internalType": "uint256",
        "name": "timestamp",
        "type": "uint256"
      }
    ],
    "name": "ReserveSnapshotted",
    "type": "event"
  },
  {
    "anonymous": false,
    "inputs": [
      {
        "indexed": false,
        "internalType": "uint256",
        "name": "settlementPrice",
        "type": "uint256"
      }
    ],
    "name": "Shutdown",
    "type": "event"
  },
  {
    "anonymous": false,
    "inputs": [
      {
        "indexed": false,
        "internalType": "enum IExchangeTypes.Dir",
        "name": "dir",
        "type": "uint8"
      },
      {
        "indexed": false,
        "internalType": "uint256",
        "name": "quoteAssetAmount",
        "type": "uint256"
      },
      {
        "indexed": false,
        "internalType": "uint256",
        "name": "baseAssetAmount",
        "type": "uint256"
      }
    ],
    "name": "SwapInput",
    "type": "event"
  },
  {
    "anonymous": false,
    "inputs": [
      {
        "indexed": false,
        "internalType": "enum IExchangeTypes.Dir",
        "name": "dir",
        "type": "uint8"
      },
      {
        "indexed": false,
        "internalType": "uint256",
        "name": "quoteAssetAmount",
        "type": "uint256"
      },
      {
        "indexed": false,
        "internalType": "uint256",
        "name": "baseAssetAmount",
        "type": "uint256"
      }
    ],
    "name": "SwapOutput",
    "type": "event"
  },
  {
    "inputs": [],
    "name": "baseAssetReserve",
    "outputs": [
      {
        "internalType": "uint256",
        "name": "d",
        "type": "uint256"
      }
    ],
    "stateMutability": "view",
    "type": "function"
  },
  {
    "inputs": [],
    "name": "fluctuationLimitRatio",
    "outputs": [
      {
        "internalType": "uint256",
        "name": "d",
        "type": "uint256"
      }
    ],
    "stateMutability": "view",
    "type": "function"
  },
  {
    "inputs": [],
    "name": "fundingBufferPeriod",
    "outputs": [
      {
        "internalType": "uint256",
        "name": "",
        "type": "uint256"
      }
    ],
    "stateMutability": "view",
    "type": "function"
  },
  {
    "inputs": [],
    "name": "fundingPeriod",
    "outputs": [
      {
        "internalType": "uint256",
        "name": "",
        "type": "uint256"
      }
    ],
    "stateMutability": "view",
    "type": "function"
  },
  {
    "inputs": [],
    "name": "fundingRate",
    "outputs": [
      {
        "internalType": "int256",
        "name": "d",
        "type": "int256"
      }
    ],
    "stateMutability": "view",
    "type": "function"
  },
  {
    "inputs": [],
    "name": "lastMoveAmmPriceTime",
    "outputs": [
      {
        "internalType": "uint256",
        "name": "",
        "type": "uint256"
      }
    ],
    "stateMutability": "view",
    "type": "function"
  },
  {
    "inputs": [],
    "name": "mover",
    "outputs": [
      {
        "internalType": "address",
        "name": "",
        "type": "address"
      }
    ],
    "stateMutability": "view",
    "type": "function"
  },
  {
    "inputs": [],
    "name": "nextFundingTime",
    "outputs": [
      {
        "internalType": "uint256",
        "name": "",
        "type": "uint256"
      }
    ],
    "stateMutability": "view",
    "type": "function"
  },
  {
    "inputs": [],
    "name": "open",
    "outputs": [
      {
        "internalType": "bool",
        "name": "",
        "type": "bool"
      }
    ],
    "stateMutability": "view",
    "type": "function"
  },
  {
    "inputs": [],
    "name": "oraclePriceSpreadLimit",
    "outputs": [
      {
        "internalType": "uint256",
        "name": "d",
        "type": "uint256"
      }
    ],
    "stateMutability": "view",
    "type": "function"
  },
  {
    "inputs": [],
    "name": "owner",
    "outputs": [
      {
        "internalType": "address",
        "name": "",
        "type": "address"
      }
    ],
    "stateMutability": "view",
    "type": "function"
  },
  {
    "inputs": [],
    "name": "priceAdjustRatio",
    "outputs": [
      {
        "internalType": "uint256",
        "name": "d",
        "type": "uint256"
      }
    ],
    "stateMutability": "view",
    "type": "function"
  },
  {
    "inputs": [],
    "name": "priceFeed",
    "outputs": [
      {
        "internalType": "contract IPriceFeed",
        "name": "",
        "type": "address"
      }
    ],
    "stateMutability": "view",
    "type": "function"
  },
  {
    "inputs": [],
    "name": "priceFeedKey",
    "outputs": [
      {
        "internalType": "bytes32",
        "name": "",
        "type": "bytes32"
      }
    ],
    "stateMutability": "view",
    "type": "function"
  },
  {
    "inputs": [],
    "name": "quoteAsset",
    "outputs": [
      {
        "internalType": "contract IERC20Upgradeable",
        "name": "",
        "type": "address"
      }
    ],
    "stateMutability": "view",
    "type": "function"
  },
  {
    "inputs": [],
    "name": "quoteAssetReserve",
    "outputs": [
      {
        "internalType": "uint256",
        "name": "d",
        "type": "uint256"
      }
    ],
    "stateMutability": "view",
    "type": "function"
  },
  {
    "inputs": [],
    "name": "renounceOwnership",
    "outputs": [],
    "stateMutability": "nonpayable",
    "type": "function"
  },
  {
    "inputs": [
      {
        "internalType": "uint256",
        "name": "",
        "type": "uint256"
      }
    ],
    "name": "reserveSnapshots",
    "outputs": [
      {
        "components": [
          {
            "internalType": "uint256",
            "name": "d",
            "type": "uint256"
          }
        ],
        "internalType": "struct Decimal.decimal",
        "name": "quoteAssetReserve",
        "type": "tuple"
      },
      {
        "components": [
          {
            "internalType": "uint256",
            "name": "d",
            "type": "uint256"
          }
        ],
        "internalType": "struct Decimal.decimal",
        "name": "baseAssetReserve",
        "type": "tuple"
      },
      {
        "internalType": "uint256",
        "name": "timestamp",
        "type": "uint256"
      },
      {
        "internalType": "uint256",
        "name": "blockNumber",
        "type": "uint256"
      }
    ],
    "stateMutability": "view",
    "type": "function"
  },
  {
    "inputs": [],
    "name": "sakePerp",
    "outputs": [
      {
        "internalType": "contract ISakePerp",
        "name": "",
        "type": "address"
      }
    ],
    "stateMutability": "view",
    "type": "function"
  },
  {
    "inputs": [],
    "name": "sakePerpVault",
    "outputs": [
      {
        "internalType": "contract ISakePerpVault",
        "name": "",
        "type": "address"
      }
    ],
    "stateMutability": "view",
    "type": "function"
  },
  {
    "inputs": [],
    "name": "spotPriceTwapInterval",
    "outputs": [
      {
        "internalType": "uint256",
        "name": "",
        "type": "uint256"
      }
    ],
    "stateMutability": "view",
    "type": "function"
  },
  {
    "inputs": [],
    "name": "totalPositionSize",
    "outputs": [
      {
        "internalType": "int256",
        "name": "d",
        "type": "int256"
      }
    ],
    "stateMutability": "view",
    "type": "function"
  },
  {
    "inputs": [],
    "name": "tradeLimitRatio",
    "outputs": [
      {
        "internalType": "uint256",
        "name": "d",
        "type": "uint256"
      }
    ],
    "stateMutability": "view",
    "type": "function"
  },
  {
    "inputs": [
      {
        "internalType": "address",
        "name": "newOwner",
        "type": "address"
      }
    ],
    "name": "transferOwnership",
    "outputs": [],
    "stateMutability": "nonpayable",
    "type": "function"
  },
  {
    "inputs": [
      {
        "internalType": "uint256",
        "name": "_quoteAssetReserve",
        "type": "uint256"
      },
      {
        "internalType": "uint256",
        "name": "_baseAssetReserve",
        "type": "uint256"
      },
      {
        "internalType": "uint256",
        "name": "_tradeLimitRatio",
        "type": "uint256"
      },
      {
        "internalType": "uint256",
        "name": "_fundingPeriod",
        "type": "uint256"
      },
      {
        "internalType": "contract IPriceFeed",
        "name": "_priceFeed",
        "type": "address"
      },
      {
        "internalType": "contract ISakePerp",
        "name": "_sakePerp",
        "type": "address"
      },
      {
        "internalType": "contract ISakePerpVault",
        "name": "_sakePerpVault",
        "type": "address"
      },
      {
        "internalType": "bytes32",
        "name": "_priceFeedKey",
        "type": "bytes32"
      },
      {
        "internalType": "address",
        "name": "_quoteAsset",
        "type": "address"
      },
      {
        "internalType": "uint256",
        "name": "_fluctuationLimitRatio",
        "type": "uint256"
      },
      {
        "internalType": "uint256",
        "name": "_priceAdjustRatio",
        "type": "uint256"
      },
      {
        "internalType": "contract IExchangeState",
        "name": "_exchangeState",
        "type": "address"
      }
    ],
    "name": "initialize",
    "outputs": [],
    "stateMutability": "nonpayable",
    "type": "function"
  },
  {
    "inputs": [
      {
        "internalType": "enum ISakePerpVaultTypes.Risk",
        "name": "_risk",
        "type": "uint8"
      },
      {
        "internalType": "address",
        "name": "account",
        "type": "address"
      },
      {
        "internalType": "uint256",
        "name": "amount",
        "type": "uint256"
      }
    ],
    "name": "mint",
    "outputs": [],
    "stateMutability": "nonpayable",
    "type": "function"
  },
  {
    "inputs": [
      {
        "internalType": "enum ISakePerpVaultTypes.Risk",
        "name": "_risk",
        "type": "uint8"
      },
      {
        "internalType": "address",
        "name": "account",
        "type": "address"
      },
      {
        "internalType": "uint256",
        "name": "amount",
        "type": "uint256"
      }
    ],
    "name": "burn",
    "outputs": [],
    "stateMutability": "nonpayable",
    "type": "function"
  },
  {
    "inputs": [
      {
        "internalType": "enum IExchangeTypes.Dir",
        "name": "_dir",
        "type": "uint8"
      },
      {
        "components": [
          {
            "internalType": "uint256",
            "name": "d",
            "type": "uint256"
          }
        ],
        "internalType": "struct Decimal.decimal",
        "name": "_quoteAssetAmount",
        "type": "tuple"
      },
      {
        "components": [
          {
            "internalType": "uint256",
            "name": "d",
            "type": "uint256"
          }
        ],
        "internalType": "struct Decimal.decimal",
        "name": "_baseAssetAmountLimit",
        "type": "tuple"
      }
    ],
    "name": "swapInput",
    "outputs": [
      {
        "components": [
          {
            "internalType": "uint256",
            "name": "d",
            "type": "uint256"
          }
        ],
        "internalType": "struct Decimal.decimal",
        "name": "",
        "type": "tuple"
      }
    ],
    "stateMutability": "nonpayable",
    "type": "function"
  },
  {
    "inputs": [
      {
        "internalType": "enum IExchangeTypes.Dir",
        "name": "_dir",
        "type": "uint8"
      },
      {
        "components": [
          {
            "internalType": "uint256",
            "name": "d",
            "type": "uint256"
          }
        ],
        "internalType": "struct Decimal.decimal",
        "name": "_baseAssetAmount",
        "type": "tuple"
      },
      {
        "components": [
          {
            "internalType": "uint256",
            "name": "d",
            "type": "uint256"
          }
        ],
        "internalType": "struct Decimal.decimal",
        "name": "_quoteAssetAmountLimit",
        "type": "tuple"
      },
      {
        "internalType": "bool",
        "name": "_skipFluctuationCheck",
        "type": "bool"
      }
    ],
    "name": "swapOutput",
    "outputs": [
      {
        "components": [
          {
            "internalType": "uint256",
            "name": "d",
            "type": "uint256"
          }
        ],
        "internalType": "struct Decimal.decimal",
        "name": "",
        "type": "tuple"
      }
    ],
    "stateMutability": "nonpayable",
    "type": "function"
  },
  {
    "inputs": [],
    "name": "settleFunding",
    "outputs": [
      {
        "components": [
          {
            "internalType": "int256",
            "name": "d",
            "type": "int256"
          }
        ],
        "internalType": "struct SignedDecimal.signedDecimal",
        "name": "",
        "type": "tuple"
      }
    ],
    "stateMutability": "nonpayable",
    "type": "function"
  },
  {
    "inputs": [
      {
        "components": [
          {
            "internalType": "uint256",
            "name": "d",
            "type": "uint256"
          }
        ],
        "internalType": "struct Decimal.decimal",
        "name": "_liquidityMultiplier",
        "type": "tuple"
      },
      {
        "components": [
          {
            "internalType": "uint256",
            "name": "d",
            "type": "uint256"
          }
        ],
        "internalType": "struct Decimal.decimal",
        "name": "_fluctuationLimitRatio",
        "type": "tuple"
      }
    ],
    "name": "migrateLiquidity",
    "outputs": [],
    "stateMutability": "nonpayable",
    "type": "function"
  },
  {
    "inputs": [
      {
        "components": [
          {
            "internalType": "int256",
            "name": "d",
            "type": "int256"
          }
        ],
        "internalType": "struct SignedDecimal.signedDecimal",
        "name": "_baseAssetAmount",
        "type": "tuple"
      },
      {
        "components": [
          {
            "internalType": "uint256",
            "name": "d",
            "type": "uint256"
          }
        ],
        "internalType": "struct Decimal.decimal",
        "name": "_fromQuoteReserve",
        "type": "tuple"
      },
      {
        "components": [
          {
            "internalType": "uint256",
            "name": "d",
            "type": "uint256"
          }
        ],
        "internalType": "struct Decimal.decimal",
        "name": "_fromBaseReserve",
        "type": "tuple"
      }
    ],
    "name": "calcBaseAssetAfterLiquidityMigration",
    "outputs": [
      {
        "components": [
          {
            "internalType": "int256",
            "name": "d",
            "type": "int256"
          }
        ],
        "internalType": "struct SignedDecimal.signedDecimal",
        "name": "",
        "type": "tuple"
      }
    ],
    "stateMutability": "view",
    "type": "function"
  },
  {
    "inputs": [],
    "name": "shutdown",
    "outputs": [],
    "stateMutability": "nonpayable",
    "type": "function"
  },
  {
    "inputs": [
      {
        "internalType": "address",
        "name": "_counterParty",
        "type": "address"
      }
    ],
    "name": "setCounterParty",
    "outputs": [],
    "stateMutability": "nonpayable",
    "type": "function"
  },
  {
    "inputs": [
      {
        "internalType": "address",
        "name": "_minter",
        "type": "address"
      }
    ],
    "name": "setMinter",
    "outputs": [],
    "stateMutability": "nonpayable",
    "type": "function"
  },
  {
    "inputs": [
      {
        "components": [
          {
            "internalType": "uint256",
            "name": "d",
            "type": "uint256"
          }
        ],
        "internalType": "struct Decimal.decimal",
        "name": "_fluctuationLimitRatio",
        "type": "tuple"
      }
    ],
    "name": "setFluctuationLimitRatio",
    "outputs": [],
    "stateMutability": "nonpayable",
    "type": "function"
  },
  {
    "inputs": [
      {
        "internalType": "uint256",
        "name": "_interval",
        "type": "uint256"
      }
    ],
    "name": "setSpotPriceTwapInterval",
    "outputs": [],
    "stateMutability": "nonpayable",
    "type": "function"
  },
  {
    "inputs": [
      {
        "internalType": "bool",
        "name": "_open",
        "type": "bool"
      }
    ],
    "name": "setOpen",
    "outputs": [],
    "stateMutability": "nonpayable",
    "type": "function"
  },
  {
    "inputs": [
      {
        "components": [
          {
            "internalType": "uint256",
            "name": "d",
            "type": "uint256"
          }
        ],
        "internalType": "struct Decimal.decimal",
        "name": "_priceAdjustRatio",
        "type": "tuple"
      }
    ],
    "name": "setPriceAdjustRatio",
    "outputs": [],
    "stateMutability": "nonpayable",
    "type": "function"
  },
  {
    "inputs": [
      {
        "internalType": "address",
        "name": "_priceFeed",
        "type": "address"
      }
    ],
    "name": "setPriceFeed",
    "outputs": [],
    "stateMutability": "nonpayable",
    "type": "function"
  },
  {
    "inputs": [
      {
        "components": [
          {
            "internalType": "uint256",
            "name": "d",
            "type": "uint256"
          }
        ],
        "internalType": "struct Decimal.decimal",
        "name": "_limit",
        "type": "tuple"
      }
    ],
    "name": "setOraclePriceSpreadLimit",
    "outputs": [],
    "stateMutability": "nonpayable",
    "type": "function"
  },
  {
    "inputs": [
      {
        "internalType": "address",
        "name": "_newMover",
        "type": "address"
      }
    ],
    "name": "setMover",
    "outputs": [],
    "stateMutability": "nonpayable",
    "type": "function"
  },
  {
    "inputs": [
      {
        "internalType": "address",
        "name": "_exchangeState",
        "type": "address"
      }
    ],
    "name": "setExchangeState",
    "outputs": [],
    "stateMutability": "nonpayable",
    "type": "function"
  },
  {
    "inputs": [
      {
        "internalType": "enum IExchangeTypes.Dir",
        "name": "_dir",
        "type": "uint8"
      },
      {
        "components": [
          {
            "internalType": "uint256",
            "name": "d",
            "type": "uint256"
          }
        ],
        "internalType": "struct Decimal.decimal",
        "name": "_quoteAssetAmount",
        "type": "tuple"
      }
    ],
    "name": "getInputTwap",
    "outputs": [
      {
        "components": [
          {
            "internalType": "uint256",
            "name": "d",
            "type": "uint256"
          }
        ],
        "internalType": "struct Decimal.decimal",
        "name": "",
        "type": "tuple"
      }
    ],
    "stateMutability": "view",
    "type": "function"
  },
  {
    "inputs": [
      {
        "internalType": "enum IExchangeTypes.Dir",
        "name": "_dir",
        "type": "uint8"
      },
      {
        "components": [
          {
            "internalType": "uint256",
            "name": "d",
            "type": "uint256"
          }
        ],
        "internalType": "struct Decimal.decimal",
        "name": "_baseAssetAmount",
        "type": "tuple"
      }
    ],
    "name": "getOutputTwap",
    "outputs": [
      {
        "components": [
          {
            "internalType": "uint256",
            "name": "d",
            "type": "uint256"
          }
        ],
        "internalType": "struct Decimal.decimal",
        "name": "",
        "type": "tuple"
      }
    ],
    "stateMutability": "view",
    "type": "function"
  },
  {
    "inputs": [
      {
        "internalType": "enum IExchangeTypes.Dir",
        "name": "_dir",
        "type": "uint8"
      },
      {
        "components": [
          {
            "internalType": "uint256",
            "name": "d",
            "type": "uint256"
          }
        ],
        "internalType": "struct Decimal.decimal",
        "name": "_quoteAssetAmount",
        "type": "tuple"
      }
    ],
    "name": "getInputPrice",
    "outputs": [
      {
        "components": [
          {
            "internalType": "uint256",
            "name": "d",
            "type": "uint256"
          }
        ],
        "internalType": "struct Decimal.decimal",
        "name": "",
        "type": "tuple"
      }
    ],
    "stateMutability": "view",
    "type": "function"
  },
  {
    "inputs": [
      {
        "internalType": "enum IExchangeTypes.Dir",
        "name": "_dir",
        "type": "uint8"
      },
      {
        "components": [
          {
            "internalType": "uint256",
            "name": "d",
            "type": "uint256"
          }
        ],
        "internalType": "struct Decimal.decimal",
        "name": "_baseAssetAmount",
        "type": "tuple"
      }
    ],
    "name": "getOutputPrice",
    "outputs": [
      {
        "components": [
          {
            "internalType": "uint256",
            "name": "d",
            "type": "uint256"
          }
        ],
        "internalType": "struct Decimal.decimal",
        "name": "",
        "type": "tuple"
      }
    ],
    "stateMutability": "view",
    "type": "function"
  },
  {
    "inputs": [],
    "name": "getUnderlyingPrice",
    "outputs": [
      {
        "components": [
          {
            "internalType": "uint256",
            "name": "d",
            "type": "uint256"
          }
        ],
        "internalType": "struct Decimal.decimal",
        "name": "",
        "type": "tuple"
      }
    ],
    "stateMutability": "view",
    "type": "function"
  },
  {
    "inputs": [
      {
        "internalType": "uint256",
        "name": "_intervalInSeconds",
        "type": "uint256"
      }
    ],
    "name": "getUnderlyingTwapPrice",
    "outputs": [
      {
        "components": [
          {
            "internalType": "uint256",
            "name": "d",
            "type": "uint256"
          }
        ],
        "internalType": "struct Decimal.decimal",
        "name": "",
        "type": "tuple"
      }
    ],
    "stateMutability": "view",
    "type": "function"
  },
  {
    "inputs": [],
    "name": "getSpotPrice",
    "outputs": [
      {
        "components": [
          {
            "internalType": "uint256",
            "name": "d",
            "type": "uint256"
          }
        ],
        "internalType": "struct Decimal.decimal",
        "name": "",
        "type": "tuple"
      }
    ],
    "stateMutability": "view",
    "type": "function"
  },
  {
    "inputs": [
      {
        "internalType": "uint256",
        "name": "_intervalInSeconds",
        "type": "uint256"
      }
    ],
    "name": "getTwapPrice",
    "outputs": [
      {
        "components": [
          {
            "internalType": "uint256",
            "name": "d",
            "type": "uint256"
          }
        ],
        "internalType": "struct Decimal.decimal",
        "name": "",
        "type": "tuple"
      }
    ],
    "stateMutability": "view",
    "type": "function"
  },
  {
    "inputs": [],
    "name": "getReserve",
    "outputs": [
      {
        "components": [
          {
            "internalType": "uint256",
            "name": "d",
            "type": "uint256"
          }
        ],
        "internalType": "struct Decimal.decimal",
        "name": "",
        "type": "tuple"
      },
      {
        "components": [
          {
            "internalType": "uint256",
            "name": "d",
            "type": "uint256"
          }
        ],
        "internalType": "struct Decimal.decimal",
        "name": "",
        "type": "tuple"
      }
    ],
    "stateMutability": "view",
    "type": "function"
  },
  {
    "inputs": [],
    "name": "getSnapshotLen",
    "outputs": [
      {
        "internalType": "uint256",
        "name": "",
        "type": "uint256"
      }
    ],
    "stateMutability": "view",
    "type": "function"
  },
  {
    "inputs": [],
    "name": "getLiquidityHistoryLength",
    "outputs": [
      {
        "internalType": "uint256",
        "name": "",
        "type": "uint256"
      }
    ],
    "stateMutability": "view",
    "type": "function"
  },
  {
    "inputs": [],
    "name": "getCumulativeNotional",
    "outputs": [
      {
        "components": [
          {
            "internalType": "int256",
            "name": "d",
            "type": "int256"
          }
        ],
        "internalType": "struct SignedDecimal.signedDecimal",
        "name": "",
        "type": "tuple"
      }
    ],
    "stateMutability": "view",
    "type": "function"
  },
  {
    "inputs": [],
    "name": "getLatestLiquidityChangedSnapshots",
    "outputs": [
      {
        "components": [
          {
            "components": [
              {
                "internalType": "int256",
                "name": "d",
                "type": "int256"
              }
            ],
            "internalType": "struct SignedDecimal.signedDecimal",
            "name": "cumulativeNotional",
            "type": "tuple"
          },
          {
            "components": [
              {
                "internalType": "uint256",
                "name": "d",
                "type": "uint256"
              }
            ],
            "internalType": "struct Decimal.decimal",
            "name": "quoteAssetReserve",
            "type": "tuple"
          },
          {
            "components": [
              {
                "internalType": "uint256",
                "name": "d",
                "type": "uint256"
              }
            ],
            "internalType": "struct Decimal.decimal",
            "name": "baseAssetReserve",
            "type": "tuple"
          },
          {
            "components": [
              {
                "internalType": "int256",
                "name": "d",
                "type": "int256"
              }
            ],
            "internalType": "struct SignedDecimal.signedDecimal",
            "name": "totalPositionSize",
            "type": "tuple"
          }
        ],
        "internalType": "struct IExchangeTypes.LiquidityChangedSnapshot",
        "name": "",
        "type": "tuple"
      }
    ],
    "stateMutability": "view",
    "type": "function"
  },
  {
    "inputs": [
      {
        "internalType": "uint256",
        "name": "i",
        "type": "uint256"
      }
    ],
    "name": "getLiquidityChangedSnapshots",
    "outputs": [
      {
        "components": [
          {
            "components": [
              {
                "internalType": "int256",
                "name": "d",
                "type": "int256"
              }
            ],
            "internalType": "struct SignedDecimal.signedDecimal",
            "name": "cumulativeNotional",
            "type": "tuple"
          },
          {
            "components": [
              {
                "internalType": "uint256",
                "name": "d",
                "type": "uint256"
              }
            ],
            "internalType": "struct Decimal.decimal",
            "name": "quoteAssetReserve",
            "type": "tuple"
          },
          {
            "components": [
              {
                "internalType": "uint256",
                "name": "d",
                "type": "uint256"
              }
            ],
            "internalType": "struct Decimal.decimal",
            "name": "baseAssetReserve",
            "type": "tuple"
          },
          {
            "components": [
              {
                "internalType": "int256",
                "name": "d",
                "type": "int256"
              }
            ],
            "internalType": "struct SignedDecimal.signedDecimal",
            "name": "totalPositionSize",
            "type": "tuple"
          }
        ],
        "internalType": "struct IExchangeTypes.LiquidityChangedSnapshot",
        "name": "",
        "type": "tuple"
      }
    ],
    "stateMutability": "view",
    "type": "function"
  },
  {
    "inputs": [],
    "name": "getSettlementPrice",
    "outputs": [
      {
        "components": [
          {
            "internalType": "uint256",
            "name": "d",
            "type": "uint256"
          }
        ],
        "internalType": "struct Decimal.decimal",
        "name": "",
        "type": "tuple"
      }
    ],
    "stateMutability": "view",
    "type": "function"
  },
  {
    "inputs": [],
    "name": "getMaxHoldingBaseAsset",
    "outputs": [
      {
        "components": [
          {
            "internalType": "uint256",
            "name": "d",
            "type": "uint256"
          }
        ],
        "internalType": "struct Decimal.decimal",
        "name": "",
        "type": "tuple"
      }
    ],
    "stateMutability": "view",
    "type": "function"
  },
  {
    "inputs": [],
    "name": "getOpenInterestNotionalCap",
    "outputs": [
      {
        "components": [
          {
            "internalType": "uint256",
            "name": "d",
            "type": "uint256"
          }
        ],
        "internalType": "struct Decimal.decimal",
        "name": "",
        "type": "tuple"
      }
    ],
    "stateMutability": "view",
    "type": "function"
  },
  {
    "inputs": [],
    "name": "initMarginRatio",
    "outputs": [
      {
        "components": [
          {
            "internalType": "uint256",
            "name": "d",
            "type": "uint256"
          }
        ],
        "internalType": "struct Decimal.decimal",
        "name": "",
        "type": "tuple"
      }
    ],
    "stateMutability": "view",
    "type": "function"
  },
  {
    "inputs": [],
    "name": "maintenanceMarginRatio",
    "outputs": [
      {
        "components": [
          {
            "internalType": "uint256",
            "name": "d",
            "type": "uint256"
          }
        ],
        "internalType": "struct Decimal.decimal",
        "name": "",
        "type": "tuple"
      }
    ],
    "stateMutability": "view",
    "type": "function"
  },
  {
    "inputs": [],
    "name": "liquidationFeeRatio",
    "outputs": [
      {
        "components": [
          {
            "internalType": "uint256",
            "name": "d",
            "type": "uint256"
          }
        ],
        "internalType": "struct Decimal.decimal",
        "name": "",
        "type": "tuple"
      }
    ],
    "stateMutability": "view",
    "type": "function"
  },
  {
    "inputs": [],
    "name": "maxLiquidationFee",
    "outputs": [
      {
        "components": [
          {
            "internalType": "uint256",
            "name": "d",
            "type": "uint256"
          }
        ],
        "internalType": "struct Decimal.decimal",
        "name": "",
        "type": "tuple"
      }
    ],
    "stateMutability": "view",
    "type": "function"
  },
  {
    "inputs": [],
    "name": "spreadRatio",
    "outputs": [
      {
        "components": [
          {
            "internalType": "uint256",
            "name": "d",
            "type": "uint256"
          }
        ],
        "internalType": "struct Decimal.decimal",
        "name": "",
        "type": "tuple"
      }
    ],
    "stateMutability": "view",
    "type": "function"
  },
  {
    "inputs": [],
    "name": "getTotalPositionSize",
    "outputs": [
      {
        "components": [
          {
            "internalType": "int256",
            "name": "d",
            "type": "int256"
          }
        ],
        "internalType": "struct SignedDecimal.signedDecimal",
        "name": "",
        "type": "tuple"
      }
    ],
    "stateMutability": "view",
    "type": "function"
  },
  {
    "inputs": [],
    "name": "getExchangeState",
    "outputs": [
      {
        "internalType": "address",
        "name": "",
        "type": "address"
      }
    ],
    "stateMutability": "view",
    "type": "function"
  },
  {
    "inputs": [],
    "name": "isOverSpreadLimit",
    "outputs": [
      {
        "internalType": "bool",
        "name": "",
        "type": "bool"
      }
    ],
    "stateMutability": "view",
    "type": "function"
  },
  {
    "inputs": [
      {
        "components": [
          {
            "internalType": "uint256",
            "name": "d",
            "type": "uint256"
          }
        ],
        "internalType": "struct Decimal.decimal",
        "name": "_quoteAssetAmount",
        "type": "tuple"
      }
    ],
    "name": "calcFee",
    "outputs": [
      {
        "components": [
          {
            "internalType": "uint256",
            "name": "d",
            "type": "uint256"
          }
        ],
        "internalType": "struct Decimal.decimal",
        "name": "",
        "type": "tuple"
      }
    ],
    "stateMutability": "view",
    "type": "function"
  },
  {
    "inputs": [
      {
        "internalType": "enum IExchangeTypes.Dir",
        "name": "_dir",
        "type": "uint8"
      },
      {
        "components": [
          {
            "internalType": "uint256",
            "name": "d",
            "type": "uint256"
          }
        ],
        "internalType": "struct Decimal.decimal",
        "name": "_quoteAssetAmount",
        "type": "tuple"
      },
      {
        "components": [
          {
            "internalType": "uint256",
            "name": "d",
            "type": "uint256"
          }
        ],
        "internalType": "struct Decimal.decimal",
        "name": "_quoteAssetPoolAmount",
        "type": "tuple"
      },
      {
        "components": [
          {
            "internalType": "uint256",
            "name": "d",
            "type": "uint256"
          }
        ],
        "internalType": "struct Decimal.decimal",
        "name": "_baseAssetPoolAmount",
        "type": "tuple"
      }
    ],
    "name": "getInputPriceWithReserves",
    "outputs": [
      {
        "components": [
          {
            "internalType": "uint256",
            "name": "d",
            "type": "uint256"
          }
        ],
        "internalType": "struct Decimal.decimal",
        "name": "",
        "type": "tuple"
      }
    ],
    "stateMutability": "view",
    "type": "function"
  },
  {
    "inputs": [
      {
        "internalType": "enum IExchangeTypes.Dir",
        "name": "_dir",
        "type": "uint8"
      },
      {
        "components": [
          {
            "internalType": "uint256",
            "name": "d",
            "type": "uint256"
          }
        ],
        "internalType": "struct Decimal.decimal",
        "name": "_baseAssetAmount",
        "type": "tuple"
      },
      {
        "components": [
          {
            "internalType": "uint256",
            "name": "d",
            "type": "uint256"
          }
        ],
        "internalType": "struct Decimal.decimal",
        "name": "_quoteAssetPoolAmount",
        "type": "tuple"
      },
      {
        "components": [
          {
            "internalType": "uint256",
            "name": "d",
            "type": "uint256"
          }
        ],
        "internalType": "struct Decimal.decimal",
        "name": "_baseAssetPoolAmount",
        "type": "tuple"
      }
    ],
    "name": "getOutputPriceWithReserves",
    "outputs": [
      {
        "components": [
          {
            "internalType": "uint256",
            "name": "d",
            "type": "uint256"
          }
        ],
        "internalType": "struct Decimal.decimal",
        "name": "",
        "type": "tuple"
      }
    ],
    "stateMutability": "view",
    "type": "function"
  },
  {
    "inputs": [
      {
        "internalType": "uint256",
        "name": "_oraclePrice",
        "type": "uint256"
      },
      {
        "internalType": "bytes32",
        "name": "_priceFeedKey",
        "type": "bytes32"
      }
    ],
    "name": "moveAMMPriceToOracle",
    "outputs": [],
    "stateMutability": "nonpayable",
    "type": "function"
  },
  {
    "inputs": [
      {
        "components": [
          {
            "internalType": "uint256",
            "name": "d",
            "type": "uint256"
          }
        ],
        "internalType": "struct Decimal.decimal",
        "name": "_baseAssetReserve",
        "type": "tuple"
      },
      {
        "components": [
          {
            "internalType": "uint256",
            "name": "d",
            "type": "uint256"
          }
        ],
        "internalType": "struct Decimal.decimal",
        "name": "_quoteAssetReserve",
        "type": "tuple"
      }
    ],
    "name": "getMMUnrealizedPNL",
    "outputs": [
      {
        "components": [
          {
            "internalType": "int256",
            "name": "d",
            "type": "int256"
          }
        ],
        "internalType": "struct SignedDecimal.signedDecimal",
        "name": "",
        "type": "tuple"
      }
    ],
    "stateMutability": "view",
    "type": "function"
  },
  {
    "inputs": [
      {
        "components": [
          {
            "internalType": "int256",
            "name": "d",
            "type": "int256"
          }
        ],
        "internalType": "struct SignedDecimal.signedDecimal",
        "name": "adjustedPosition",
        "type": "tuple"
      },
      {
        "components": [
          {
            "internalType": "int256",
            "name": "d",
            "type": "int256"
          }
        ],
        "internalType": "struct SignedDecimal.signedDecimal",
        "name": "oldAdjustedPosition",
        "type": "tuple"
      }
    ],
    "name": "adjustTotalPosition",
    "outputs": [],
    "stateMutability": "nonpayable",
    "type": "function"
  }
]
